PyMines-1.2.3.dist-info/DESCRIPTION.rst
PyMines-1.2.3.dist-info/METADATA
PyMines-1.2.3.dist-info/RECORD
PyMines-1.2.3.dist-info/WHEEL
PyMines-1.2.3.dist-info/entry_points.txt
PyMines-1.2.3.dist-info/metadata.json
PyMines-1.2.3.dist-info/top_level.txt
pymines/pymines.py
pymines/images/face_dead.png
pymines/images/face_normal.png
pymines/images/tile_1.png
pymines/images/tile_2.png
pymines/images/tile_3.png
pymines/images/tile_4.png
pymines/images/tile_5.png
pymines/images/tile_6.png
pymines/images/tile_7.png
pymines/images/tile_8.png
pymines/images/tile_clicked.png
pymines/images/tile_flag.png
pymines/images/tile_mine.png
pymines/images/tile_plain.png
