Metadata-Version: 2.0
Name: PyMines
Version: 1.2.3
Summary: Very simple minesweeper game
Home-page: https://github.com/Vilsol/PyMines
Author: Vilsol
Author-email: me@vil.so
License: UNKNOWN
Platform: UNKNOWN
